min_dotenv-0.1.0.dist-info/METADATA
min_dotenv-0.1.0.dist-info/WHEEL
min_dotenv-0.1.0.dist-info/licenses/LICENSE
min_dotenv/__init__.py
min_dotenv/min_dotenv.abi3.so
min_dotenv-0.1.0.dist-info/RECORD
