Metadata-Version: 2.4
Name: min_dotenv
Version: 0.1.0
Classifier: Development Status :: 1 - Planning
Classifier: License :: OSI Approved :: MIT License
Classifier: Programming Language :: Rust
Classifier: Topic :: Software Development :: Libraries :: Python Modules
License-File: LICENSE
Summary: A minimal dotenv loader for Python, written in Rust.
Keywords: automation,environmental,variables,dotenv
Author-email: Raúl Telo Sánchez <raultelo@gmail.com>
Requires-Python: >=3.12
Project-URL: Repository, https://github.com/lRaulMN7/min_dotenv
Project-URL: Changelog, https://github.com/lRaulMN7/min_dotenv/blob/main/CHANGELOG.md
